kogniterm/__init__.py
kogniterm/main.py
kogniterm/requirements.txt
kogniterm/core/__init__.py
kogniterm/core/agent_state.py
kogniterm/core/command_executor.py
kogniterm/core/config.py
kogniterm/core/embeddings_service.py
kogniterm/core/exceptions.py
kogniterm/core/history_manager.py
kogniterm/core/llm_bridge.py
kogniterm/core/llm_service.py
kogniterm/core/llm_service_enhanced.py
kogniterm/core/progress_manager.py
kogniterm/core/session_manager.py
kogniterm/core/agents/__init__.py
kogniterm/core/agents/bash_agent.py
kogniterm/core/agents/code_agent.py
kogniterm/core/agents/code_crew.py
kogniterm/core/agents/code_crew_agents.py
kogniterm/core/agents/research_agents.py
kogniterm/core/agents/researcher_agent.py
kogniterm/core/agents/researcher_agent_backup.py
kogniterm/core/agents/researcher_crew.py
kogniterm/core/agents/specialized_agents.py
kogniterm/core/context/__init__.py
kogniterm/core/context/codebase_indexer.py
kogniterm/core/context/vector_db_manager.py
kogniterm/core/context/workspace_context.py
kogniterm/core/tools/__init__.py
kogniterm/core/tools/advanced_file_editor_tool.py
kogniterm/core/tools/brave_search_tool.py
kogniterm/core/tools/call_agent_tool.py
kogniterm/core/tools/code_analysis_tool.py
kogniterm/core/tools/codebase_search_tool.py
kogniterm/core/tools/execute_command_tool.py
kogniterm/core/tools/file_operations_tool.py
kogniterm/core/tools/file_read_directory_tool.py
kogniterm/core/tools/file_search_tool.py
kogniterm/core/tools/file_update_tool.py
kogniterm/core/tools/github_tool.py
kogniterm/core/tools/memory_append_tool.py
kogniterm/core/tools/memory_init_tool.py
kogniterm/core/tools/memory_read_tool.py
kogniterm/core/tools/memory_summarize_tool.py
kogniterm/core/tools/pc_interaction_tool.py
kogniterm/core/tools/plan_creation_tool.py
kogniterm/core/tools/playwright_browser_manager.py
kogniterm/core/tools/pylint_tool.py
kogniterm/core/tools/python_executor.py
kogniterm/core/tools/search_memory_tool.py
kogniterm-0.1.3.dist-info/licenses/LICENSE
kogniterm-0.1.3.dist-info/METADATA
kogniterm-0.1.3.dist-info/WHEEL
kogniterm-0.1.3.dist-info/entry_points.txt
kogniterm-0.1.3.dist-info/top_level.txt
kogniterm-0.1.3.dist-info/RECORD
