Metadata-Version: 2.4
Name: kogniterm
Version: 0.1.3
Summary: KogniTerm: Tu asistente de terminal inteligente con esteroides 🚀
Author-email: Gato Villano <gato@example.com>
License: MIT
Project-URL: Homepage, https://github.com/gatovillano/KogniTerm
Project-URL: Repository, https://github.com/gatovillano/KogniTerm
Project-URL: Issues, https://github.com/gatovillano/KogniTerm/issues
Keywords: terminal,ai,agent,assistant,llm,automation
Classifier: Programming Language :: Python :: 3
Classifier: License :: OSI Approved :: MIT License
Classifier: Operating System :: OS Independent
Classifier: Development Status :: 4 - Beta
Classifier: Environment :: Console
Classifier: Intended Audience :: Developers
Requires-Python: >=3.9
License-File: LICENSE
Requires-Dist: python-dotenv
Requires-Dist: langchain
Requires-Dist: langchain-core
Requires-Dist: langgraph
Requires-Dist: prompt_toolkit
Requires-Dist: langchain_mcp_adapters
Requires-Dist: langchain_community
Requires-Dist: beautifulsoup4
Requires-Dist: PyGithub
Requires-Dist: rich
Requires-Dist: matplotlib
Requires-Dist: google-genai
Requires-Dist: jupyter_client
Requires-Dist: loguru
Requires-Dist: colorama
Requires-Dist: gitignore-parser
Requires-Dist: watchdog
Requires-Dist: litellm
Requires-Dist: playwright
Requires-Dist: GitPython
Requires-Dist: pydantic
Requires-Dist: pydantic-settings
Requires-Dist: chromadb
Requires-Dist: urllib3<2
Requires-Dist: pyautogui
Requires-Dist: pywinctl
Requires-Dist: langchain-litellm
Requires-Dist: nest_asyncio
Requires-Dist: tiktoken
Requires-Dist: requests
Requires-Dist: crewai
Provides-Extra: dev
Requires-Dist: radon; extra == "dev"
Requires-Dist: pylint; extra == "dev"
Requires-Dist: pytest; extra == "dev"
Requires-Dist: build; extra == "dev"
Requires-Dist: twine; extra == "dev"
Dynamic: license-file
